baldr/__init__.py
baldr/api.py
baldr/app.py
baldr/auth.py
baldr/content_type_resolvers.py
baldr/exceptions.py
baldr/form_fields.py
baldr/model_api.py
baldr/model_fields.py
baldr/models.py
baldr/resource_form.py
baldr/resources.py
baldr/api/__init__.py
baldr/api/constants.py
baldr/api/mixins.py
baldr/api/models.py
baldr/api/route_decorators.py
baldr/api2/__init__.py
baldr/api2/constants.py
baldr/api2/models.py
baldr/api2/route_decorators.py
baldr/tests/__init__.py
baldr/tests/test_content_type_resolvers.py
baldr/tests/test_model_fields.py
baldr-1.0.dist-info/DESCRIPTION.rst
baldr-1.0.dist-info/METADATA
baldr-1.0.dist-info/RECORD
baldr-1.0.dist-info/WHEEL
baldr-1.0.dist-info/metadata.json
baldr-1.0.dist-info/pbr.json
baldr-1.0.dist-info/top_level.txt
